graphqomb/__init__.py
graphqomb/circuit.py
graphqomb/command.py
graphqomb/common.py
graphqomb/euler.py
graphqomb/feedforward.py
graphqomb/focus_flow.py
graphqomb/gates.py
graphqomb/graphstate.py
graphqomb/matrix.py
graphqomb/pattern.py
graphqomb/pauli_frame.py
graphqomb/py.typed
graphqomb/qompiler.py
graphqomb/random_objects.py
graphqomb/rng.py
graphqomb/schedule_solver.py
graphqomb/scheduler.py
graphqomb/simulator.py
graphqomb/simulator_backend.py
graphqomb/statevec.py
graphqomb/stim_compiler.py
graphqomb/visualizer.py
graphqomb-0.2.1.dist-info/licenses/LICENSE
graphqomb-0.2.1.dist-info/METADATA
graphqomb-0.2.1.dist-info/WHEEL
graphqomb-0.2.1.dist-info/top_level.txt
graphqomb-0.2.1.dist-info/RECORD
