Metadata-Version: 2.4
Name: graphqomb
Version: 0.2.1
Summary: A modular Graph State qompiler for measurement-based quantum computing.
Author: Sora Shiratani, Yuki Watanabe, Daichi Sasaki
Author-email: Masato Fukushima <masa1063fuk@gmail.com>
Maintainer-email: Masato Fukushima <masa1063fuk@gmail.com>
License: MIT
Project-URL: Homepage, https://github.com/TeamGraphix/graphqomb
Project-URL: Documentation, https://graphqomb.readthedocs.io/
Project-URL: Repository, https://github.com/TeamGraphix/graphqomb
Project-URL: Changelog, https://github.com/TeamGraphix/graphqomb/blob/master/CHANGELOG.md
Project-URL: Bug Tracker, https://github.com/TeamGraphix/graphqomb/issues
Keywords: quantum computing,MBQC,measurement-based quantum computing,quantum compilation,fault-tolerant quantum computing,graph state
Classifier: Development Status :: 4 - Beta
Classifier: Intended Audience :: Science/Research
Classifier: Intended Audience :: Developers
Classifier: License :: OSI Approved :: MIT License
Classifier: Programming Language :: Python :: 3
Classifier: Programming Language :: Python :: 3.10
Classifier: Programming Language :: Python :: 3.11
Classifier: Programming Language :: Python :: 3.12
Classifier: Programming Language :: Python :: 3.13
Classifier: Programming Language :: Python :: 3.14
Classifier: Topic :: Scientific/Engineering :: Physics
Classifier: Topic :: Scientific/Engineering :: Quantum Computing
Classifier: Topic :: Software Development :: Libraries :: Python Modules
Requires-Python: <3.15,>=3.10
License-File: LICENSE
Requires-Dist: numpy<3,>=1.22
Requires-Dist: matplotlib
Requires-Dist: networkx
Requires-Dist: ortools<10,>=9
Requires-Dist: typing_extensions
Provides-Extra: dev
Requires-Dist: ruff==0.14.13; extra == "dev"
Requires-Dist: mypy==1.19.1; extra == "dev"
Requires-Dist: pyright==1.1.408; extra == "dev"
Requires-Dist: pytest==9.0.2; extra == "dev"
Requires-Dist: pytest-cov; extra == "dev"
Requires-Dist: types-networkx; extra == "dev"
Provides-Extra: doc
Requires-Dist: sphinx>=7.4.0; extra == "doc"
Requires-Dist: sphinx_gallery>=0.17.0; extra == "doc"
Requires-Dist: furo>=2024.01.29; extra == "doc"
Requires-Dist: matplotlib>=3.7.0; extra == "doc"
Dynamic: license-file
